.gitignore
MANIFEST.in
setup.py
ebs/__init__.py
ebs/linuxnode/__init__.py
ebs/linuxnode/gui/__init__.py
ebs/linuxnode/gui/kivy/__init__.py
ebs/linuxnode/gui/kivy/background/__init__.py
ebs/linuxnode/gui/kivy/background/mediaplayer.py
ebs/linuxnode/gui/kivy/mediaplayer/__init__.py
ebs/linuxnode/gui/kivy/mediaplayer/manager.py
ebs/linuxnode/gui/kivy/mediaplayer/mixin.py
ebs/linuxnode/gui/kivy/mediaplayer/players/__init__.py
ebs/linuxnode/gui/kivy/mediaplayer/players/image.py
ebs/linuxnode/gui/kivy/mediaplayer/players/pdf.py
ebs/linuxnode/gui/kivy/mediaplayer/players/video.py
ebs/linuxnode/mediaplayer/__init__.py
ebs/linuxnode/mediaplayer/base.py
ebs/linuxnode/mediaplayer/manager.py
ebs/linuxnode/mediaplayer/mixin.py
ebs_linuxnode_gui_kivy_mediaplayer.egg-info/PKG-INFO
ebs_linuxnode_gui_kivy_mediaplayer.egg-info/SOURCES.txt
ebs_linuxnode_gui_kivy_mediaplayer.egg-info/dependency_links.txt
ebs_linuxnode_gui_kivy_mediaplayer.egg-info/requires.txt
ebs_linuxnode_gui_kivy_mediaplayer.egg-info/top_level.txt
example/app.py
example/image.jpg
example/node.py
example/pdf.pdf
example/run.py
example/video-2.mp4
example/video.mp4